sqlobject_adapter/__init__.py
sqlobject_adapter/adapter.py
sqlobject_adapter-0.5.0.dist-info/licenses/LICENSE
sqlobject_adapter-0.5.0.dist-info/METADATA
sqlobject_adapter-0.5.0.dist-info/WHEEL
sqlobject_adapter-0.5.0.dist-info/top_level.txt
sqlobject_adapter-0.5.0.dist-info/RECORD
