Metadata-Version: 2.4
Name: sqlobject_adapter
Version: 0.5.0
Summary: SQLObject Adapter for PyCasbin
Author-email: Casbin <admin@casbin.org>
License: Apache 2.0
Project-URL: Home-page, https://github.com/officialpycasbin/sqlobject-adapter
Keywords: casbin,SQLObject,casbin-adapter,rbac,access control,abac,acl,permission
Classifier: Programming Language :: Python :: 3.4
Classifier: Programming Language :: Python :: 3.5
Classifier: Programming Language :: Python :: 3.6
Classifier: Programming Language :: Python :: 3.7
Classifier: Programming Language :: Python :: 3.8
Classifier: Programming Language :: Python :: 3.9
Classifier: Programming Language :: Python :: 3.10
Classifier: Programming Language :: Python :: 3.11
Classifier: Programming Language :: Python :: 3.12
Classifier: License :: OSI Approved :: Apache Software License
Classifier: Operating System :: OS Independent
Requires-Python: >=3.4
License-File: LICENSE
Requires-Dist: pycasbin>=2.0.0
Requires-Dist: SQLObject>=3.8.0
Dynamic: license-file
